steinloss/Data_Presenter.py
steinloss/__init__.py
steinloss/__main__.py
steinloss/loss_calculator.py
steinloss/package.py
steinloss/probe.py
steinloss/server.py
steinloss/stein_parser.py
steinloss/utilities.py
steinloss/dashboard/__init__.py
steinloss/dashboard/dashboard.py
steinloss-0.3.6.dist-info/LICENSE
steinloss-0.3.6.dist-info/METADATA
steinloss-0.3.6.dist-info/WHEEL
steinloss-0.3.6.dist-info/entry_points.txt
steinloss-0.3.6.dist-info/top_level.txt
steinloss-0.3.6.dist-info/RECORD
