Metadata-Version: 2.1
Name: steinloss
Version: 0.3.6
Summary: Package loss measuring tool
Home-page: https://github.com/steinwurf/steinloss
Author: Steinwurf ApS
Author-email: contact@steinwurf.com
License: UNKNOWN
Platform: UNKNOWN
Classifier: Programming Language :: Python :: 3
Classifier: License :: OSI Approved :: MIT License
Classifier: Operating System :: OS Independent
Classifier: Environment :: Console
Classifier: Environment :: Web Environment
Classifier: Framework :: Dash
Requires-Python: >=3.7
Requires-Dist: plotly (~=4.12.0)
Requires-Dist: pandas (~=1.1.4)
Requires-Dist: dash (~=1.13.4)
Requires-Dist: asyncio-dgram (~=1.1.1)
Requires-Dist: Flask (~=1.1.2)
Requires-Dist: matplotlib
Requires-Dist: hurry.filesize (~=0.9)
